testcontainers/elasticsearch/__init__.py
tests/test_elasticsearch.py
testcontainers_elasticsearch-0.0.1rc1.dist-info/METADATA
testcontainers_elasticsearch-0.0.1rc1.dist-info/WHEEL
testcontainers_elasticsearch-0.0.1rc1.dist-info/top_level.txt
testcontainers_elasticsearch-0.0.1rc1.dist-info/RECORD
